clooey/__init__.py
clooey/clooey.py
clooey/main.py
clooey/examples/password.py
clooey/examples/piglatin.py
clooey/examples/sample.py
clooey-0.1.1.dist-info/LICENSE
clooey-0.1.1.dist-info/METADATA
clooey-0.1.1.dist-info/WHEEL
clooey-0.1.1.dist-info/entry_points.txt
clooey-0.1.1.dist-info/top_level.txt
clooey-0.1.1.dist-info/RECORD
