Metadata-Version: 2.1
Name: clooey
Version: 0.1.1
Summary: Converts CLIs into web forms
Author-email: Alvin Wan <hi@alvinwan.com>
License: MIT License
Project-URL: Homepage, https://github.com/alvinwan/clooey
Classifier: Programming Language :: Python :: 3
Classifier: License :: OSI Approved :: MIT License
Classifier: Operating System :: OS Independent
Requires-Python: >=3.7
License-File: LICENSE
Requires-Dist: jinja2
